synology_api/__init__.py
synology_api/abm.py
synology_api/audiostation.py
synology_api/auth.py
synology_api/base_api.py
synology_api/cloud_sync.py
synology_api/core_active_backup.py
synology_api/core_backup.py
synology_api/core_certificate.py
synology_api/core_group.py
synology_api/core_package.py
synology_api/core_share.py
synology_api/core_sys_info.py
synology_api/core_user.py
synology_api/dhcp_server.py
synology_api/directory_server.py
synology_api/docker_api.py
synology_api/downloadstation.py
synology_api/drive_admin_console.py
synology_api/error_codes.py
synology_api/event_scheduler.py
synology_api/exceptions.py
synology_api/filestation.py
synology_api/log_center.py
synology_api/notestation.py
synology_api/oauth.py
synology_api/photos.py
synology_api/security_advisor.py
synology_api/snapshot.py
synology_api/surveillancestation.py
synology_api/task_scheduler.py
synology_api/universal_search.py
synology_api/usb_copy.py
synology_api/utils.py
synology_api/virtualization.py
synology_api/vpn.py
synology_api-0.8.2.dist-info/licenses/LICENSE.txt
synology_api-0.8.2.dist-info/METADATA
synology_api-0.8.2.dist-info/WHEEL
synology_api-0.8.2.dist-info/top_level.txt
synology_api-0.8.2.dist-info/RECORD
