Metadata-Version: 2.4
Name: synology-api
Version: 0.8.2
Summary: Python Synology API Wrapper
Home-page: https://github.com/N4S4/synology-api
Author: Renato Visaggio
Author-email: synology.python.api@gmail.com
License: MIT
License-File: LICENSE.txt
Requires-Dist: requests
Requires-Dist: urllib3
Requires-Dist: setuptools
Requires-Dist: requests_toolbelt
Requires-Dist: tqdm
Requires-Dist: cryptography
Requires-Dist: treelib
Requires-Dist: noiseprotocol
Dynamic: author
Dynamic: author-email
Dynamic: description
Dynamic: description-content-type
Dynamic: home-page
Dynamic: license
Dynamic: license-file
Dynamic: requires-dist
Dynamic: summary
